wgrd_cons_tools/__init__.py
wgrd_cons_tools/create_vfs.py
wgrd_cons_tools/decode_ess.py
wgrd_cons_tools/edat_helper.py
wgrd_cons_tools/encode_ess.py
wgrd_cons_tools/generate_sformat.py
wgrd_cons_tools/helper_dds.py
wgrd_cons_tools/tgv_dds_tool.py
wgrd_cons_tools/unpack_wgrd.py
wgrd_cons_tools/utils.py
wgrd_cons_tools/version.py
wgrd_cons_tools/wgrd_patch_exe.py
wgrd_cons_tools-0.3.dist-info/licenses/LICENSE
wgrd_cons_tools-0.3.dist-info/METADATA
wgrd_cons_tools-0.3.dist-info/WHEEL
wgrd_cons_tools-0.3.dist-info/top_level.txt
wgrd_cons_tools-0.3.dist-info/RECORD
