Metadata-Version: 2.4
Name: wgrd_cons_tools
Version: 0.3
Summary: Tools for working with the xml files generated by wgrd_cons_parsers for modding the game Wargame: Red Dragon.
Author-email: End <wgrd@3nd.io>
Requires-Python: >=3.10
License-File: LICENSE
Requires-Dist: conshex
Requires-Dist: wgrd-cons-parsers
Requires-Dist: pytest
Dynamic: license-file
